ai_edge_quantizer/__init__.py
ai_edge_quantizer/algorithm_manager.py
ai_edge_quantizer/algorithm_manager_api.py
ai_edge_quantizer/algorithm_manager_api_test.py
ai_edge_quantizer/calibrator.py
ai_edge_quantizer/calibrator_test.py
ai_edge_quantizer/conftest.py
ai_edge_quantizer/default_policy.py
ai_edge_quantizer/model_modifier.py
ai_edge_quantizer/model_modifier_test.py
ai_edge_quantizer/model_validator.py
ai_edge_quantizer/model_validator_test.py
ai_edge_quantizer/params_generator.py
ai_edge_quantizer/params_generator_test.py
ai_edge_quantizer/qtyping.py
ai_edge_quantizer/quantizer.py
ai_edge_quantizer/quantizer_test.py
ai_edge_quantizer/recipe.py
ai_edge_quantizer/recipe_manager.py
ai_edge_quantizer/recipe_manager_test.py
ai_edge_quantizer/recipe_test.py
ai_edge_quantizer/transformation_instruction_generator.py
ai_edge_quantizer/transformation_instruction_generator_test.py
ai_edge_quantizer/transformation_performer.py
ai_edge_quantizer/transformation_performer_test.py
ai_edge_quantizer/algorithms/__init__.py
ai_edge_quantizer/algorithms/nonlinear_quantize/__init__.py
ai_edge_quantizer/algorithms/nonlinear_quantize/float_casting.py
ai_edge_quantizer/algorithms/nonlinear_quantize/float_casting_test.py
ai_edge_quantizer/algorithms/uniform_quantize/__init__.py
ai_edge_quantizer/algorithms/uniform_quantize/common_quantize.py
ai_edge_quantizer/algorithms/uniform_quantize/common_quantize_test.py
ai_edge_quantizer/algorithms/uniform_quantize/dequantized_weight_recovery.py
ai_edge_quantizer/algorithms/uniform_quantize/dequantized_weight_recovery_test.py
ai_edge_quantizer/algorithms/uniform_quantize/hadamard_rotation.py
ai_edge_quantizer/algorithms/uniform_quantize/hadamard_rotation_test.py
ai_edge_quantizer/algorithms/uniform_quantize/mse.py
ai_edge_quantizer/algorithms/uniform_quantize/mse_test.py
ai_edge_quantizer/algorithms/uniform_quantize/naive_min_max_quantize.py
ai_edge_quantizer/algorithms/uniform_quantize/naive_min_max_quantize_test.py
ai_edge_quantizer_nightly-0.5.0.dev20260201.dist-info/licenses/LICENSE
ai_edge_quantizer_nightly-0.5.0.dev20260201.dist-info/METADATA
ai_edge_quantizer_nightly-0.5.0.dev20260201.dist-info/WHEEL
ai_edge_quantizer_nightly-0.5.0.dev20260201.dist-info/top_level.txt
ai_edge_quantizer_nightly-0.5.0.dev20260201.dist-info/RECORD
